<?xml version="1.0" encoding="utf-8" ?>
<dwsync>
<file name="tbd1.png" server="pluto1019.cafe24.com//www/samsungtv/" local="3547257435" remote="319783739191090288" Dst="-1" />
<file name="tbd2.png" server="pluto1019.cafe24.com//www/samsungtv/" local="3547257452" remote="319783739191090288" Dst="-1" />
<file name="tbd4.png" server="pluto1019.cafe24.com//www/samsungtv/" local="3547257484" remote="319783739191090288" Dst="-1" />
<file name="tbd5.png" server="pluto1019.cafe24.com//www/samsungtv/" local="3547257500" remote="319783739191090288" Dst="-1" />
<file name="tbd3.png" server="pluto1019.cafe24.com//www/samsungtv/" local="3547257470" remote="319783739191090288" Dst="-1" />
<file name="slide01.png" server="pluto1019.cafe24.com//www/samsungtv/" local="3547258030" remote="319783739191090768" Dst="-1" />
<file name="slide02.png" server="pluto1019.cafe24.com//www/samsungtv/" local="3547258076" remote="319783739191090768" Dst="-1" />
<file name="slide03.png" server="pluto1019.cafe24.com//www/samsungtv/" local="3547258063" remote="319783739191090768" Dst="-1" />
<file name="slide04.png" server="pluto1019.cafe24.com//www/samsungtv/" local="3547258090" remote="319783739191090768" Dst="-1" />
<file name="1.png" server="pluto1019.cafe24.com//www/tv/" local="131109508504709914" remote="131109185400000000" Dst="0" />
<file name="slide01.png" server="pluto1019.cafe24.com//www/tv/" local="131098580998642450" remote="131098269000000000" Dst="0" />
<file name="slide02.png" server="pluto1019.cafe24.com//www/tv/" local="131088868760000000" remote="131098269000000000" Dst="0" />
<file name="slide03.png" server="pluto1019.cafe24.com//www/tv/" local="131088868640000000" remote="131098269000000000" Dst="0" />
<file name="slide04.png" server="pluto1019.cafe24.com//www/tv/" local="131088868900000000" remote="131098269000000000" Dst="0" />
<file name="tbd1.png" server="pluto1019.cafe24.com//www/tv/" local="131098577332232743" remote="131098269000000000" Dst="0" />
<file name="tbd2.png" server="pluto1019.cafe24.com//www/tv/" local="131098577637970230" remote="131098269000000000" Dst="0" />
<file name="tbd3.png" server="pluto1019.cafe24.com//www/tv/" local="131088862700000000" remote="131098269000000000" Dst="0" />
<file name="tbd4.png" server="pluto1019.cafe24.com//www/tv/" local="131088862840000000" remote="131098269000000000" Dst="0" />
<file name="tbd5.png" server="pluto1019.cafe24.com//www/tv/" local="131088863000000000" remote="131098269000000000" Dst="0" />
<file name=".DS_Store" server="pluto1019.cafe24.com//www/tv/" local="131099347297455585" remote="131092890000000000" Dst="0" />
</dwsync>